dh_client/__init__.py
dh_client/client.py
dh_client/entities/__init__.py
dh_client/entities/custom_properties.py
dh_client/entities/dashboards.py
dh_client/entities/data_jobs.py
dh_client/entities/datasets.py
dh_client/entities/glossary_terms.py
dh_client/entities/links.py
dh_client/entities/owners.py
dh_client/entities/tags.py
dh_client/entities/users.py
dh_client/exceptions.py
dh_client/utils.py
dh_client-0.1.22.dist-info/WHEEL
dh_client-0.1.22.dist-info/METADATA
dh_client-0.1.22.dist-info/RECORD
