Metadata-Version: 2.1
Name: dh-client
Version: 0.1.22
Summary: A high level python client for datahub.
License: Apache-2.0
Author: Netdata Inc.
Requires-Python: >=3.7,<4.0
Classifier: License :: OSI Approved :: Apache Software License
Classifier: Programming Language :: Python :: 3
Classifier: Programming Language :: Python :: 3.10
Classifier: Programming Language :: Python :: 3.7
Classifier: Programming Language :: Python :: 3.8
Classifier: Programming Language :: Python :: 3.9
Requires-Dist: acryl-datahub (>=0.8.26)
